kaisia/__init__.py
kaisia/auth.py
kaisia/cli.py
kaisia/config.py
kaisia/exceptions.py
kaisia/gbq.py
kaisia/main.py
kaisia/version.py
kaisia-0.0.4.dist-info/METADATA
kaisia-0.0.4.dist-info/WHEEL
kaisia-0.0.4.dist-info/entry_points.txt
kaisia-0.0.4.dist-info/licenses/LICENSE
kaisia-0.0.4.dist-info/RECORD
